Metadata-Version: 1.0
Name: py2-ipaddress
Version: 2.0
Summary: Python 2.7 backport of 3.3's ipaddress module
Home-page: https://bitbucket.org/kwi/py2-ipaddress/
Author: Søren Løvborg
Author-email: kwi@kwi.dk
License: Python Software Foundation License version 2
Platform: UNKNOWN
Classifier: Development Status :: 5 - Production/Stable
Classifier: Intended Audience :: Developers
Classifier: License :: OSI Approved :: Python Software Foundation License
Classifier: Programming Language :: Python :: 2.7
Classifier: Topic :: Internet
Classifier: Topic :: System :: Networking
